hnews/__init__.py
hnews/__main__.py
hnews/parser.py
hnews/scraper.py
hnews/ui.py
hnews/validator.py
py_hacker_news-1.0.4.dist-info/LICENSE
py_hacker_news-1.0.4.dist-info/METADATA
py_hacker_news-1.0.4.dist-info/WHEEL
py_hacker_news-1.0.4.dist-info/entry_points.txt
py_hacker_news-1.0.4.dist-info/top_level.txt
py_hacker_news-1.0.4.dist-info/RECORD
