Metadata-Version: 2.1
Name: py-hacker-news
Version: 1.0.4
Summary: Command Line tool for browsing HackerNews articles
Home-page: https://github.com/saivarshith2000/hacker_news_cli
Author: saivarshith2000
Author-email: hosvarshith@gmail.com
License: MIT
Platform: UNKNOWN
Classifier: License :: OSI Approved :: MIT License
Classifier: Programming Language :: Python :: 3
Classifier: Programming Language :: Python :: 3.7
Requires-Dist: beautifulsoup4
Requires-Dist: requests
